{
  "n": 82,
  "accuracy": 0.976,
  "confusion": {
    "benefits_perks": {
      "benefits_perks": 4
    },
    "legal_boilerplate": {
      "legal_boilerplate": 5
    },
    "mission_brand": {
      "mission_brand": 36,
      "job_listing": 1
    },
    "job_listing": {
      "job_listing": 33,
      "process_logistics": 1
    },
    "process_logistics": {
      "process_logistics": 2
    }
  },
  "disagreements": [
    {
      "chunk_id": "59786296b8dafa66",
      "hand_label": "mission_brand",
      "predicted": "job_listing"
    },
    {
      "chunk_id": "9650eb07e0633817",
      "hand_label": "job_listing",
      "predicted": "process_logistics"
    }
  ]
}